asyncwowapi/__init__.py
asyncwowapi/api.py
asyncwowapi/api_client.py
asyncwowapi/battle_net/__init__.py
asyncwowapi/battle_net/auth.py
asyncwowapi/battle_net/oauth_client.py
asyncwowapi/exceptions.py
asyncwowapi/utils.py
asyncwowapi/validators.py
asyncwowapi/wow/GameData.py
asyncwowapi/wow/Profile.py
asyncwowapi/wow/Profile_modules/AccountProfile.py
asyncwowapi/wow/Profile_modules/CharacterAchievements.py
asyncwowapi/wow/Profile_modules/CharacterAppearance.py
asyncwowapi/wow/Profile_modules/CharacterCollections.py
asyncwowapi/wow/Profile_modules/CharacterEncounters.py
asyncwowapi/wow/Profile_modules/CharacterEquipment.py
asyncwowapi/wow/Profile_modules/CharacterHunterPets.py
asyncwowapi/wow/Profile_modules/CharacterMedia.py
asyncwowapi/wow/Profile_modules/CharacterMythicKeystoneProfile.py
asyncwowapi/wow/Profile_modules/CharacterProfessions.py
asyncwowapi/wow/Profile_modules/CharacterProfile.py
asyncwowapi/wow/Profile_modules/CharacterPvP.py
asyncwowapi/wow/Profile_modules/CharacterQuests.py
asyncwowapi/wow/Profile_modules/CharacterReputations.py
asyncwowapi/wow/Profile_modules/CharacterSoulbinds.py
asyncwowapi/wow/Profile_modules/CharacterSpecializations.py
asyncwowapi/wow/Profile_modules/CharacterStatistics.py
asyncwowapi/wow/Profile_modules/CharacterTitles.py
asyncwowapi/wow/Profile_modules/Guild.py
asyncwowapi/wow/Profile_modules/__init__.py
asyncwowapi/wow/__init__.py
asyncwowapi/wow/gameData_modules/Achievement.py
asyncwowapi/wow/gameData_modules/AuctionHouse.py
asyncwowapi/wow/gameData_modules/AzeriteEssence.py
asyncwowapi/wow/gameData_modules/ConnectedRealm.py
asyncwowapi/wow/gameData_modules/Covenant.py
asyncwowapi/wow/gameData_modules/Creature.py
asyncwowapi/wow/gameData_modules/GuildCrest.py
asyncwowapi/wow/gameData_modules/Heirloom.py
asyncwowapi/wow/gameData_modules/Item.py
asyncwowapi/wow/gameData_modules/Journal.py
asyncwowapi/wow/gameData_modules/MediaSearch.py
asyncwowapi/wow/gameData_modules/ModifiedCrafting.py
asyncwowapi-0.1.1.dist-info/LICENSE
asyncwowapi-0.1.1.dist-info/METADATA
asyncwowapi-0.1.1.dist-info/WHEEL
asyncwowapi-0.1.1.dist-info/RECORD
