Metadata-Version: 2.1
Name: asyncWowApi
Version: 0.1.1
Summary: 
License: MIT
Author: angeloffy
Author-email: angeloffy.work@gmail.com
Requires-Python: >=3.12,<4.0
Classifier: License :: OSI Approved :: MIT License
Classifier: Programming Language :: Python :: 3
Classifier: Programming Language :: Python :: 3.12
Requires-Dist: aiohttp (>=3.9.5,<4.0.0)
Requires-Dist: pydantic (>=2.7.3,<3.0.0)
